tsimpute/__init__.py
tsimpute/core/__init__.py
tsimpute/core/alias.py
tsimpute/core/config.py
tsimpute/core/data.py
tsimpute/core/logger.py
tsimpute/core/plot.py
tsimpute/core/utils.py
tsimpute/core/validate.py
tsimpute/modules/__init__.py
tsimpute/modules/combine/__init__.py
tsimpute/modules/combine/base.py
tsimpute/modules/combine/common.py
tsimpute/modules/combine/half_t.py
tsimpute/modules/combine/meow.py
tsimpute/modules/combine/wbdi.py
tsimpute/modules/metric/__init__.py
tsimpute/modules/metric/base.py
tsimpute/modules/metric/common.py
tsimpute/modules/models/__init__.py
tsimpute/modules/models/base.py
tsimpute/modules/models/cnn1d/__init__.py
tsimpute/modules/models/cnn1d/attn.py
tsimpute/modules/models/cnn1d/v1.py
tsimpute/modules/models/cnn1d/v2.py
tsimpute/modules/models/cnn1d/v3.py
tsimpute/modules/models/common.py
tsimpute/modules/models/dynamic.py
tsimpute/modules/models/peri_midformer/__init__.py
tsimpute/modules/models/peri_midformer/attn.py
tsimpute/modules/models/peri_midformer/embed.py
tsimpute/modules/models/peri_midformer/enc_dec.py
tsimpute/modules/models/peri_midformer/utils.py
tsimpute/modules/models/transformers/__init__.py
tsimpute/modules/models/transformers/attn.py
tsimpute/modules/models/transformers/mh_attn.py
tsimpute/modules/models/transformers/transformer.py
tsimpute/modules/preprocess/__init__.py
tsimpute/modules/preprocess/base.py
tsimpute/modules/preprocess/outlier.py
tsimpute/modules/preprocess/scaler.py
tsimpute/modules/trainer/__init__.py
tsimpute/modules/trainer/base.py
tsimpute/modules/trainer/bidirectional.py
tsimpute/plugins/__init__.py
tsimpute/plugins/mlflow.py
tsimpute-0.1.0.dist-info/METADATA
tsimpute-0.1.0.dist-info/WHEEL
tsimpute-0.1.0.dist-info/RECORD
